<?xml version="1.0" encoding="UTF-8" ?>
<!DOCTYPE generatorConfiguration PUBLIC "-//mybatis.org//DTD MyBatis Generator Configuration 1.0//EN" "http://mybatis.org/dtd/mybatis-generator-config_1_0.dtd">

<generatorConfiguration>
  <context id="handsOnTables" targetRuntime="MyBatis3">

    <!-- Connection Settings -->
    <jdbcConnection driverClass="org.h2.Driver"
        connectionURL="jdbc:h2:../workspace/product-manage-site-service-for-hands-on/h2db/sampledb"
        userId="username"
        password="password">
    </jdbcConnection>

    <!-- Entity Models -->
    <javaModelGenerator targetPackage="com.example.demo.entity.domain" targetProject="product-manage-site-service-for-hands-on/src/main/java">
      <property name="enableSubPackages" value="true" />
      <property name="trimStrings" value="true" />
    </javaModelGenerator>

    <!-- Sql Xml files -->
    <sqlMapGenerator targetPackage="com.example.demo.mybatis" targetProject="product-manage-site-service-for-hands-on/src/main/resources">
      <property name="enableSubPackages" value="true" />
    </sqlMapGenerator>

    <!-- Mappers -->
    <javaClientGenerator type="XMLMAPPER" targetPackage="com.example.demo.mybatis" targetProject="product-manage-site-service-for-hands-on/src/main/java">
      <property name="enableSubPackages" value="true" />
    </javaClientGenerator>

    <!-- Target tables -->
    <table schema="" tableName="USER_MST">
      <property name="mapUnderscoreToCamelCase" value="true" />
    </table>
    <table schema="" tableName="PRODUCT_MST">
      <property name="mapUnderscoreToCamelCase" value="true" />
    </table>
    <table schema="" tableName="PRODUCT_STOCK_MST">
      <property name="mapUnderscoreToCamelCase" value="true" />
    </table>
    <table schema="" tableName="PRODUCT_PURCHASE_TBL">
      <property name="mapUnderscoreToCamelCase" value="true" />
    </table>
    <table schema="" tableName="SUB_MENU_MST">
      <property name="mapUnderscoreToCamelCase" value="true" />
    </table>
    <table schema="" tableName="MENU_MST">
      <property name="mapUnderscoreToCamelCase" value="true" />
    </table>

  </context>
</generatorConfiguration>